openweights/__init__.py
openweights/cli/__init__.py
openweights/cli/__main__.py
openweights/cli/cancel.py
openweights/cli/cluster.py
openweights/cli/common.py
openweights/cli/deploy.py
openweights/cli/env.py
openweights/cli/exec.py
openweights/cli/fetch.py
openweights/cli/logs.py
openweights/cli/ls.py
openweights/cli/manage.py
openweights/cli/serve.py
openweights/cli/signup.py
openweights/cli/ssh.py
openweights/cli/token.py
openweights/cli/worker.py
openweights/client/__init__.py
openweights/client/chat.py
openweights/client/decorators.py
openweights/client/events.py
openweights/client/files.py
openweights/client/jobs.py
openweights/client/run.py
openweights/client/temporary_api.py
openweights/client/utils.py
openweights/cluster/.gitignore
openweights/cluster/org_manager.py
openweights/cluster/start_runpod.py
openweights/cluster/supervisor.py
openweights/dashboard/backend/database.py
openweights/dashboard/backend/main.py
openweights/dashboard/backend/models.py
openweights/dashboard/backend/utils.py
openweights/dashboard/backend/static/index.html
openweights/dashboard/backend/static/ow.svg
openweights/dashboard/backend/static/vite.svg
openweights/dashboard/backend/static/assets/LogProbVisualization-B6jQtzzK.js
openweights/dashboard/backend/static/assets/LogProbVisualization-CnEzdbXa.js
openweights/dashboard/backend/static/assets/LogProbVisualization-DChAruH-.js
openweights/dashboard/backend/static/assets/MetricsPlots-BzYzp0RD.js
openweights/dashboard/backend/static/assets/MetricsPlots-Do-0PbcE.js
openweights/dashboard/backend/static/assets/MetricsPlots-Dy5N4URR.js
openweights/dashboard/backend/static/assets/browser-CHCO931n.js
openweights/dashboard/backend/static/assets/browser-DG1xBqer.js
openweights/dashboard/backend/static/assets/browser-tfbTCamV.js
openweights/dashboard/backend/static/assets/index-CL2BTY-B.js
openweights/dashboard/backend/static/assets/index-CmfXCDny.js
openweights/dashboard/backend/static/assets/index-DpYPsR6j.css
openweights-0.8.0.dist-info/METADATA
openweights-0.8.0.dist-info/WHEEL
openweights-0.8.0.dist-info/entry_points.txt
openweights-0.8.0.dist-info/licenses/LICENSE.txt
openweights-0.8.0.dist-info/RECORD
