Metadata-Version: 2.4
Name: openweights
Version: 0.8.0
Summary: An openai-like sdk for finetuning and batch inference
License: MIT
License-File: LICENSE.txt
Requires-Python: >=3.11
Requires-Dist: cachier
Requires-Dist: diskcache
Requires-Dist: fastapi
Requires-Dist: fire
Requires-Dist: httpx>=0.24.0
Requires-Dist: httpx[http2]
Requires-Dist: huggingface-hub
Requires-Dist: ipykernel>=6.29.5
Requires-Dist: ipython>=9.3.0
Requires-Dist: jupyterlab>=4.4.3
Requires-Dist: openai
Requires-Dist: pyjwt
Requires-Dist: python-dotenv
Requires-Dist: runpod
Requires-Dist: scp
Requires-Dist: supabase
Requires-Dist: uvicorn
Provides-Extra: dev
Requires-Dist: black; extra == 'dev'
Requires-Dist: isort; extra == 'dev'
Requires-Dist: pre-commit; extra == 'dev'
Requires-Dist: pytest-asyncio>=0.21.0; extra == 'dev'
Requires-Dist: pytest>=7.0.0; extra == 'dev'
Provides-Extra: worker
Requires-Dist: datasets>=3.6.0; extra == 'worker'
Requires-Dist: tokenizers>=0.21.1; extra == 'worker'
Requires-Dist: torch>=2.7.1; extra == 'worker'
Requires-Dist: transformers>=4.52.4; extra == 'worker'
Requires-Dist: trl>=0.18.1; extra == 'worker'
Requires-Dist: unsloth>=2024.8; extra == 'worker'
